vedLogger/__init__.py
vedLogger/vedLogger.py
vedLogger-0.0.2.dist-info/METADATA
vedLogger-0.0.2.dist-info/WHEEL
vedLogger-0.0.2.dist-info/top_level.txt
vedLogger-0.0.2.dist-info/RECORD
