Metadata-Version: 2.1
Name: vedLogger
Version: 0.0.2
Summary: Second package of mVedr
Home-page: https://pypi.org/project/vedLogger/
Author: Ved Recharla
Author-email: vedrecharla@gmail.com
License: MIT
Classifier: Programming Language :: Python :: 3.8
